ragpackai/__init__.py
ragpackai/cli.py
ragpackai/pipeline.py
ragpackai/providers.py
ragpackai/ragpackai.py
ragpackai/storage.py
ragpackai/embeddings/__init__.py
ragpackai/embeddings/google.py
ragpackai/embeddings/huggingface.py
ragpackai/embeddings/openai.py
ragpackai/llms/__init__.py
ragpackai/llms/cerebras.py
ragpackai/llms/google.py
ragpackai/llms/groq.py
ragpackai/llms/openai.py
ragpackai-0.1.4.dist-info/licenses/LICENSE
ragpackai-0.1.4.dist-info/METADATA
ragpackai-0.1.4.dist-info/WHEEL
ragpackai-0.1.4.dist-info/entry_points.txt
ragpackai-0.1.4.dist-info/top_level.txt
ragpackai-0.1.4.dist-info/RECORD
