Metadata-Version: 2.4
Name: ragpackai
Version: 0.1.4
Summary: Portable Retrieval-Augmented Generation Library
Author-email: ragpackai Team <aistudentlearn4@gmail.com>
Maintainer-email: ragpackai Team <aistudentlearn4@gmail.com>
License: MIT
Project-URL: Homepage, https://github.com/AIMLDev726/ragpackai
Project-URL: Documentation, https://AIMLDev726.readthedocs.io/
Project-URL: Repository, https://github.com/AIMLDev726/ragpackai
Project-URL: Bug Reports, https://github.com/AIMLDev726/ragpackai/issues
Project-URL: Changelog, https://github.com/AIMLDev726/ragpackai/blob/main/CHANGELOG.md
Keywords: rag,retrieval,augmented,generation,llm,embeddings,vectorstore,ai,nlp,machine-learning,langchain
Classifier: Development Status :: 3 - Alpha
Classifier: Intended Audience :: Developers
Classifier: License :: OSI Approved :: MIT License
Classifier: Operating System :: OS Independent
Classifier: Programming Language :: Python :: 3
Classifier: Programming Language :: Python :: 3.9
Classifier: Programming Language :: Python :: 3.10
Classifier: Programming Language :: Python :: 3.11
Classifier: Programming Language :: Python :: 3.12
Classifier: Programming Language :: Python :: 3.13
Classifier: Topic :: Scientific/Engineering :: Artificial Intelligence
Classifier: Topic :: Software Development :: Libraries :: Python Modules
Requires-Python: >=3.9
License-File: LICENSE
Requires-Dist: pydantic<3.0.0,>=2.0.0
Requires-Dist: tqdm<5.0.0,>=4.60.0
Requires-Dist: cryptography<50.0.0,>=3.4.0
Provides-Extra: core
Requires-Dist: langchain<0.3.0,>=0.2.0; extra == "core"
Requires-Dist: langchain-community<0.3.0,>=0.2.0; extra == "core"
Requires-Dist: chromadb<0.6.0,>=0.5.0; extra == "core"
Requires-Dist: langchain-chroma<0.3.0,>=0.1.0; extra == "core"
Provides-Extra: documents
Requires-Dist: PyPDF2<4.0.0,>=3.0.0; extra == "documents"
Provides-Extra: embeddings
Requires-Dist: sentence-transformers<3.0.0,>=2.0.0; extra == "embeddings"
Provides-Extra: faiss
Requires-Dist: faiss-cpu<2.0.0,>=1.7.0; extra == "faiss"
Provides-Extra: openai
Requires-Dist: langchain-openai<0.2.0,>=0.1.0; extra == "openai"
Requires-Dist: openai<2.0.0,>=1.30.0; extra == "openai"
Provides-Extra: google
Requires-Dist: langchain-google-genai<2.0.0,>=1.0.0; extra == "google"
Requires-Dist: langchain-google-vertexai<2.0.0,>=1.0.0; extra == "google"
Provides-Extra: groq
Requires-Dist: groq<1.0.0,>=0.4.0; extra == "groq"
Requires-Dist: langchain-groq<1.0.0,>=0.1.0; extra == "groq"
Provides-Extra: cerebras
Requires-Dist: cerebras-cloud-sdk<2.0.0,>=1.0.0; extra == "cerebras"
Requires-Dist: langchain-cerebras<1.0.0,>=0.1.0; extra == "cerebras"
Provides-Extra: nvidia
Requires-Dist: langchain-nvidia-ai-endpoints<1.0.0,>=0.1.0; extra == "nvidia"
Provides-Extra: standard
Requires-Dist: langchain<0.3.0,>=0.2.0; extra == "standard"
Requires-Dist: langchain-community<0.3.0,>=0.2.0; extra == "standard"
Requires-Dist: langchain-openai<0.2.0,>=0.1.0; extra == "standard"
Requires-Dist: openai<2.0.0,>=1.30.0; extra == "standard"
Requires-Dist: chromadb<0.6.0,>=0.5.0; extra == "standard"
Requires-Dist: langchain-chroma<0.3.0,>=0.1.0; extra == "standard"
Requires-Dist: sentence-transformers<3.0.0,>=2.0.0; extra == "standard"
Requires-Dist: PyPDF2<4.0.0,>=3.0.0; extra == "standard"
Provides-Extra: all
Requires-Dist: langchain<0.3.0,>=0.2.0; extra == "all"
Requires-Dist: langchain-community<0.3.0,>=0.2.0; extra == "all"
Requires-Dist: langchain-openai<0.2.0,>=0.1.0; extra == "all"
Requires-Dist: openai<2.0.0,>=1.30.0; extra == "all"
Requires-Dist: chromadb<0.6.0,>=0.5.0; extra == "all"
Requires-Dist: langchain-chroma<0.3.0,>=0.1.0; extra == "all"
Requires-Dist: sentence-transformers<3.0.0,>=2.0.0; extra == "all"
Requires-Dist: PyPDF2<4.0.0,>=3.0.0; extra == "all"
Requires-Dist: faiss-cpu<2.0.0,>=1.7.0; extra == "all"
Requires-Dist: langchain-google-genai<2.0.0,>=1.0.0; extra == "all"
Requires-Dist: langchain-google-vertexai<2.0.0,>=1.0.0; extra == "all"
Requires-Dist: groq<1.0.0,>=0.4.0; extra == "all"
Requires-Dist: langchain-groq<1.0.0,>=0.1.0; extra == "all"
Requires-Dist: cerebras-cloud-sdk<2.0.0,>=1.0.0; extra == "all"
Requires-Dist: langchain-cerebras<1.0.0,>=0.1.0; extra == "all"
Requires-Dist: langchain-nvidia-ai-endpoints<1.0.0,>=0.1.0; extra == "all"
Provides-Extra: dev
Requires-Dist: pytest<8.0.0,>=7.0.0; extra == "dev"
Requires-Dist: pytest-cov<5.0.0,>=4.0.0; extra == "dev"
Requires-Dist: black<25.0.0,>=22.0.0; extra == "dev"
Requires-Dist: flake8<7.0.0,>=5.0.0; extra == "dev"
Requires-Dist: mypy<2.0.0,>=1.0.0; extra == "dev"
Requires-Dist: pre-commit<4.0.0,>=2.20.0; extra == "dev"
Requires-Dist: build<1.0.0,>=0.8.0; extra == "dev"
Requires-Dist: twine<5.0.0,>=4.0.0; extra == "dev"
Dynamic: license-file
